Workbook

Sheet Turmeric competitors
A1: Google Shopping, 'turmeric tablets', Denver CO, 28 Oct 2026 (sponsored carousel). Servings/day marked ~ are assumed.
A2: # | B2: Brand | C2: Product | D2: Format | E2: Count | F2: Servings (days) | G2: Price $ | H2: Was $ | I2: Price per day $ | J2: Rating | K2: Reviews | L2: Seller | M2: Tier | N2: Lead angle / badges | O2: Look | P2: Notes
A3: 1 | B3: Swanson | C3: Full Spectrum Turmeric 720 mg | D3: Capsule | E3: 30 | F3: 30 | G3: 5.99 | I3: =IF(F3="","",ROUND(G3/F3,2)) | J3: 4.8 | K3: 3k+ | L3: Swanson | M3: Value | N3: Whole root, joint & mobility | O3: Green, busy
A4: 2 | B4: ProHealth | C4: Optimized Curcumin Body & Joint | D4: Capsule | E4: 60 | F4: 60 | G4: 10.2 | H4: 25 | I4: =IF(F4="","",ROUND(G4/F4,2)) | J4: 4.6 | K4: 77 | L4: ProHealth | M4: Value | N4: 59% OFF | O4: Navy + stripe | P4: ~servings
A5: 3 | B5: California Gold Nutrition | C5: Curcumin 95 | D5: Capsule | E5: 30 | F5: 30 | G5: 10.27 | I5: =IF(F5="","",ROUND(G5/F5,2)) | J5: 4.8 | K5: 1k+ | L5: iHerb | M5: Value | N5: 95% curcuminoids | O5: White/gold
A6: 4 | B6: Swanson | C6: Turmeric & Black Pepper | D6: Capsule | E6: 90 | F6: 90 | G6: 13.49 | I6: =IF(F6="","",ROUND(G6/F6,2)) | J6: 4.8 | L6: Swanson | M6: Value | N6: Black pepper | O6: Green | P6: ~servings
A7: 5 | B7: Nature Made | C7: Turmeric 500 mg | D7: Capsule | E7: 60 | F7: 60 | G7: 13.99 | I7: =IF(F7="","",ROUND(G7/F7,2)) | J7: 4.7 | K7: 906 | L7: Nature Made | M7: Value | N7: USP verified, pharmacist recommended | O7: Yellow/green, busy | P7: ~servings
A8: 6 | B8: Nutrition Geeks | C8: Turmeric Tablets 2000 mg | D8: Tablet (pouch) | E8: 120 | F8: 120 | G8: 14.05 | H8: 20 | I8: =IF(F8="","",ROUND(G8/F8,2)) | J8: 4.6 | K8: 4k+ | L8: GNMart (reseller) | M8: Value | N8: Made in UK, 2000 mg, SALE | O8: Yellow/teal pouch | P8: ~servings
A9: 7 | B9: Life Extension | C9: Curcumin Elite | D9: Capsule | E9: 30 | F9: 30 | G9: 14.25 | I9: =IF(F9="","",ROUND(G9/F9,2)) | J9: 4.8 | K9: 3k+ | L9: Life Extension | M9: Value | N9: Up to 45.5x bioavailability | O9: Blue
A10: 8 | B10: NatureWise | C10: Organic Turmeric Curcumin + Ginger | D10: Capsule | E10: 90 | F10: 30 | G10: 15.44 | I10: =IF(F10="","",ROUND(G10/F10,2)) | J10: 4.7 | K10: 9k+ | L10: iHerb | M10: Value | N10: Organic, 2,250 mg/serving | O10: Red/cream
A11: 9 | B11: NOW | C11: Turmeric Curcumin | D11: Capsule | E11: 60 | F11: 45 | G11: 17.14 | I11: =IF(F11="","",ROUND(G11/F11,2)) | J11: 4.8 | K11: 5k+ | L11: iHerb | M11: Value | N11: 95% curcuminoids | O11: Orange/green | P11: ~servings
A12: 10 | B12: Future Kind | C12: Vegan Organic Turmeric | D12: Capsule | E12: 60 | F12: 30 | G12: 19 | I12: =IF(F12="","",ROUND(G12/F12,2)) | J12: 4.4 | K12: 67 | L12: Future Kind | M12: Mid | N12: #1 vegan inflammation (claim-heavy title) | O12: Amber glass, cream label
A13: 11 | B13: Global Healing | C13: Turmeric liquid 2 fl oz | D13: Liquid | G13: 24.95 | I13: =IF(F13="","",ROUND(G13/F13,2)) | J13: 4.7 | K13: 1k+ | L13: Global Healing | M13: Mid | N13: Free gift w/ $75+ | O13: Amber dropper
A14: 12 | B14: Humann | C14: Turmeric Chews | D14: Chew | E14: 30 | F14: 30 | G14: 26.95 | I14: =IF(F14="","",ROUND(G14/F14,2)) | J14: 4.3 | K14: 821 | L14: Humann | M14: Mid | N14: 90-day returns | O14: Red pouch
A15: 13 | B15: Micro Ingredients | C15: Turmeric 1000 mg | D15: Capsule | E15: 120 | F15: 90 | G15: 26.95 | I15: =IF(F15="","",ROUND(G15/F15,2)) | L15: Micro Ingredients | M15: Mid | N15: 95% curcumin | O15: White/orange | P15: ~servings
A16: 14 | B16: Momentous | C16: Turmeric | D16: Capsule | E16: 60 | F16: 30 | G16: 29.99 | H16: 40 | I16: =IF(F16="","",ROUND(G16/F16,2)) | J16: 4.7 | K16: 136 | L16: Momentous | M16: Premium | N16: 25% OFF, 1st order price (subscription) | O16: Minimal white, black type | P16: ~servings
A17: 15 | B17: BulkSupplements | C17: Turmeric Curcumin 1000 mg | D17: Capsule | E17: 240 | F17: 120 | G17: 30.97 | I17: =IF(F17="","",ROUND(G17/F17,2)) | J17: 4.6 | K17: 1k+ | L17: BulkSupplements | M17: Mid | N17: Bulk value | O17: White/orange, loud
A18: 16 | B18: Paleovalley | C18: Organic Turmeric Complex | D18: Capsule | E18: 60 | F18: 30 | G18: 34.99 | I18: =IF(F18="","",ROUND(G18/F18,2)) | J18: 4.9 | K18: 1k+ | L18: Paleovalley | M18: Premium | N18: Organic whole food | O18: Orange label
A19: 17 | B19: BetterVits | C19: Turmeric Complex (black pepper + boswellia) | D19: Capsule | E19: 60 | F19: 30 | G19: 35 | I19: =IF(F19="","",ROUND(G19/F19,2)) | L19: BetterVits | M19: Premium | N19: Free delivery; store rating 3.9/5 | O19: Pastel, white bottle, orange label | P19: ~servings
A20: 18 | B20: Thorne | C20: Curcumin Phytosome 1000 mg | D20: Capsule | E20: 60 | F20: 30 | G20: 36 | I20: =IF(F20="","",ROUND(G20/F20,2)) | J20: 4.8 | K20: 824 | L20: Thorne | M20: Premium | N20: Phytosome (clinical form) | O20: Minimal white
A21: 19 | B21: Thorne | C21: Curcumin Phytosome 1000 mg | D21: Capsule | E21: 120 | F21: 60 | G21: 64 | I21: =IF(F21="","",ROUND(G21/F21,2)) | J21: 4.8 | K21: 2k+ | L21: Thorne | M21: High | N21: Phytosome, big pack | O21: Minimal white
A22: 20 | B22: The Absorption Co. | C22: Curcumin 500 mg | D22: Capsule | E22: 60 | F22: 60 | G22: 36.75 | H22: 49 | I22: =IF(F22="","",ROUND(G22/F22,2)) | L22: Absorption Co. | M22: Premium | N22: 149x higher absorption, SALE | O22: Bold white tub, orange block | P22: ~servings
A23: 21 | B23: NAOMI | C23: Turmeric Curcumin High Potency 1200 mg | D23: Capsule | E23: 60 | F23: 30 | G23: 39.99 | I23: =IF(F23="","",ROUND(G23/F23,2)) | J23: 4.8 | K23: 48 | L23: NAOMI | M23: Premium | N23: #1 in title, 90-day returns, Clinicians' Choice | O23: Black bottle, purple + gold
A24: 22 | B24: Gaia Herbs | C24: Turmeric Supreme Extra Strength | D24: Liquid phyto-cap | E24: 120 | F24: 90 | G24: 49.49 | I24: =IF(F24="","",ROUND(G24/F24,2)) | J24: 4.7 | K24: 1k+ | L24: Gaia | M24: High | N24: Extra strength | O24: Amber + green | P24: ~servings
A25: 23 | B25: Nature's Sunshine | C25: Turmeric Curcumin 1000 mg | D25: Capsule | E25: 60 | F25: 30 | G25: 59.95 | I25: =IF(F25="","",ROUND(G25/F25,2)) | L25: Nature's Sunshine | M25: High | N25: Free delivery, trending | O25: Amber + orange | P25: ~servings
A26: 24 | B26: Vimergy | C26: Curcumin with Turmeric | D26: Capsule | E26: 270 | F26: 135 | G26: 99 | I26: =IF(F26="","",ROUND(G26/F26,2)) | J26: 4.8 | L26: vimergy | M26: High | N26: Big pack | O26: White/orange | P26: ~servings
A27: 25 | B27: Mara Labs | C27: CurcElite + BrocElite bundle | D27: Bundle | G27: 139.98 | I27: =IF(F27="","",ROUND(G27/F27,2)) | L27: Mara Labs | M27: High | N27: Bundle, trending brand | O27: Green/orange
A28: 26 | B28: Noovit (today) | C28: Turmeric Complex | D28: Capsule | E28: 60 | F28: 30 | G28: 40 | I28: =IF(F28="","",ROUND(G28/F28,2)) | L28: noovit.com | M28: Premium | N28: Evidence-graded (planned) | O28: White bottle, orange band | P28: Sub $35, 6-pack $30/bottle

Sheet Price tiers
A1: Tier | B1: Listings | C1: Min price $ | D1: Median price $ | E1: Max price $ | F1: Avg price/day $ | G1: Who | H1: Implication for Noovit
A2: Value | B2: =COUNTIF('Turmeric competitors'!M$3:M$28,A2) | C2: =MINIFS('Turmeric competitors'!G$3:G$28,'Turmeric competitors'!M$3:M$28,A2) | D2: =MEDIAN(FILTER('Turmeric competitors'!G$3:G$28,'Turmeric competitors'!M$3:M$28=A2)) | E2: =MAXIFS('Turmeric competitors'!G$3:G$28,'Turmeric competitors'!M$3:M$28,A2) | F2: =IFERROR(ROUND(AVERAGEIFS('Turmeric competitors'!I$3:I$28,'Turmeric competitors'!M$3:M$28,A2),2),"") | G2: Under $15–17, big brands, iHerb, resellers | H2: Don't compete: Supliful landed $11.05
A3: Mid | B3: =COUNTIF('Turmeric competitors'!M$3:M$28,A3) | C3: =MINIFS('Turmeric competitors'!G$3:G$28,'Turmeric competitors'!M$3:M$28,A3) | D3: =MEDIAN(FILTER('Turmeric competitors'!G$3:G$28,'Turmeric competitors'!M$3:M$28=A3)) | E3: =MAXIFS('Turmeric competitors'!G$3:G$28,'Turmeric competitors'!M$3:M$28,A3) | F3: =IFERROR(ROUND(AVERAGEIFS('Turmeric competitors'!I$3:I$28,'Turmeric competitors'!M$3:M$28,A3),2),"") | G3: Organic, chews, liquid, bulk | H3: Not our lane
A4: Premium | B4: =COUNTIF('Turmeric competitors'!M$3:M$28,A4) | C4: =MINIFS('Turmeric competitors'!G$3:G$28,'Turmeric competitors'!M$3:M$28,A4) | D4: =MEDIAN(FILTER('Turmeric competitors'!G$3:G$28,'Turmeric competitors'!M$3:M$28=A4)) | E4: =MAXIFS('Turmeric competitors'!G$3:G$28,'Turmeric competitors'!M$3:M$28,A4) | F4: =IFERROR(ROUND(AVERAGEIFS('Turmeric competitors'!I$3:I$28,'Turmeric competitors'!M$3:M$28,A4),2),"") | G4: Momentous, Paleovalley, BetterVits, Thorne, Absorption, NAOMI | H4: OUR TIER: $29–40 per bottle, $1.00–1.33/day
A5: High | B5: =COUNTIF('Turmeric competitors'!M$3:M$28,A5) | C5: =MINIFS('Turmeric competitors'!G$3:G$28,'Turmeric competitors'!M$3:M$28,A5) | D5: =MEDIAN(FILTER('Turmeric competitors'!G$3:G$28,'Turmeric competitors'!M$3:M$28=A5)) | E5: =MAXIFS('Turmeric competitors'!G$3:G$28,'Turmeric competitors'!M$3:M$28,A5) | F5: =IFERROR(ROUND(AVERAGEIFS('Turmeric competitors'!I$3:I$28,'Turmeric competitors'!M$3:M$28,A5),2),"") | G5: Gaia, Nature's Sunshine, big packs, bundles | H5: Bundles and big packs live here

Sheet Profit calculator
A1: Turmeric 60 caps via Supliful. Orange cells are inputs: change them and everything recalculates.
A3: Landed cost per bottle, free plan $ (product + shipping + fulfilment + processing) | B3: 11.05
A4: Landed cost per bottle, Pro plan $ | B4: 8
A5: Extra bottle in same order $ (product only, estimate; confirm multi-unit shipping) | B5: 4.05
A6: Stripe fee % | B6: 0.029
A7: Stripe fixed fee per order $ | B7: 0.3
A8: Ad cost to win a new customer $ (estimate) | B8: 18
A9: Supliful Pro monthly fee $ | B9: 69
A11: Pro break-even (bottles per month) | B11: =ROUND(B9/(B3-B4),0)
A13: Offer | B13: Bottles in order | C13: Price per bottle $ | D13: Order revenue $ | E13: Landed cost, free $ | F13: Stripe $ | G13: Profit, free $ | H13: Margin, free | I13: Landed cost, Pro $ | J13: Profit, Pro $ | K13: Margin, Pro | L13: Profit after ad cost (first order, free) $
A14: One-time (today) | B14: 1 | C14: 40 | D14: =B14*C14 | E14: =$B$3+(B14-1)*$B$5 | F14: =ROUND(D14*$B$6+$B$7,2) | G14: =D14-E14-F14 | H14: =G14/D14 | I14: =$B$4+(B14-1)*$B$5 | J14: =D14-I14-F14 | K14: =J14/D14 | L14: =G14-$B$8
A15: One-time (suggested) | B15: 1 | C15: 36 | D15: =B15*C15 | E15: =$B$3+(B15-1)*$B$5 | F15: =ROUND(D15*$B$6+$B$7,2) | G15: =D15-E15-F15 | H15: =G15/D15 | I15: =$B$4+(B15-1)*$B$5 | J15: =D15-I15-F15 | K15: =J15/D15 | L15: =G15-$B$8
A16: Subscribe (today) | B16: 1 | C16: 35 | D16: =B16*C16 | E16: =$B$3+(B16-1)*$B$5 | F16: =ROUND(D16*$B$6+$B$7,2) | G16: =D16-E16-F16 | H16: =G16/D16 | I16: =$B$4+(B16-1)*$B$5 | J16: =D16-I16-F16 | K16: =J16/D16 | L16: =G16-$B$8
A17: Subscribe (suggested) | B17: 1 | C17: 32 | D17: =B17*C17 | E17: =$B$3+(B17-1)*$B$5 | F17: =ROUND(D17*$B$6+$B$7,2) | G17: =D17-E17-F17 | H17: =G17/D17 | I17: =$B$4+(B17-1)*$B$5 | J17: =D17-I17-F17 | K17: =J17/D17 | L17: =G17-$B$8
A18: Subscribe (low) | B18: 1 | C18: 30 | D18: =B18*C18 | E18: =$B$3+(B18-1)*$B$5 | F18: =ROUND(D18*$B$6+$B$7,2) | G18: =D18-E18-F18 | H18: =G18/D18 | I18: =$B$4+(B18-1)*$B$5 | J18: =D18-I18-F18 | K18: =J18/D18 | L18: =G18-$B$8
A19: 3-pack one-time | B19: 3 | C19: 33 | D19: =B19*C19 | E19: =$B$3+(B19-1)*$B$5 | F19: =ROUND(D19*$B$6+$B$7,2) | G19: =D19-E19-F19 | H19: =G19/D19 | I19: =$B$4+(B19-1)*$B$5 | J19: =D19-I19-F19 | K19: =J19/D19 | L19: =G19-$B$8
A20: 6-pack one-time | B20: 6 | C20: 30 | D20: =B20*C20 | E20: =$B$3+(B20-1)*$B$5 | F20: =ROUND(D20*$B$6+$B$7,2) | G20: =D20-E20-F20 | H20: =G20/D20 | I20: =$B$4+(B20-1)*$B$5 | J20: =D20-I20-F20 | K20: =J20/D20 | L20: =G20-$B$8
A21: Supliful suggested retail | B21: 1 | C21: 25.9 | D21: =B21*C21 | E21: =$B$3+(B21-1)*$B$5 | F21: =ROUND(D21*$B$6+$B$7,2) | G21: =D21-E21-F21 | H21: =G21/D21 | I21: =$B$4+(B21-1)*$B$5 | J21: =D21-I21-F21 | K21: =J21/D21 | L21: =G21-$B$8
A23: Notes
A24: Supliful shows $4.05 – $11.05: $4.05 is the product, $11.05 is the all-in cost of one bottle delivered.
A25: Extra bottles in the same order are estimated at the product cost only. Confirm Supliful's multi-unit shipping and update B5.
A26: Ad cost is a placeholder for paid Google Shopping; subscriptions recover it over repeat orders.
A27: Competitor prices from Google Shopping on 28 Oct 2026; they change often.
